{
    "title": "An Expecting Mum",
    "articles": [{
        "title": "blah",
        "content": "Hello....",
        "image": "https://external-content.duckduckgo.com/iu/?u=https%3A%2F%2Ftse1.mm.bing.net%2Fth%3Fid%3DOIP.dGqHSRm_2NQ0euk-RgX3dAHaLH%26pid%3DApi&f=1"
    },
    {
        "title": "blah blah blah",
        "content": "HELLEKWG",
        "image": "https://external-content.duckduckgo.com/iu/?u=https%3A%2F%2Ftse4.mm.bing.net%2Fth%3Fid%3DOIP.rAGeKrmX7d1DU5fLLtGumgHaHa%26pid%3DApi&f=1"
    }]
}